txs3/__init__.py
txs3/api.py
txs3/client.py
txs3/error.py
txs3/pagination.py
txs3/signing.py
txs3/utils.py
txs3/test/__init__.py
txs3-0.1.1.dist-info/DESCRIPTION.rst
txs3-0.1.1.dist-info/entry_points.txt
txs3-0.1.1.dist-info/METADATA
txs3-0.1.1.dist-info/pydist.json
txs3-0.1.1.dist-info/RECORD
txs3-0.1.1.dist-info/top_level.txt
txs3-0.1.1.dist-info/WHEEL
