Metadata-Version: 2.0
Name: txs3
Version: 0.1.1
Summary: Amazon S3 client based on Twisted
Home-page: https://github.com/GaretJax/txs3
Author: Jonathan Stoppani
Author-email: jonathan@stoppani.name
License: MIT
Platform: UNKNOWN
Classifier: Development Status :: 4 - Beta
Classifier: Intended Audience :: Developers
Classifier: License :: OSI Approved :: MIT License
Classifier: Operating System :: OS Independent
Classifier: Programming Language :: Python
Classifier: Topic :: Software Development :: Libraries :: Python Modules
